unac/__init__.py
unac/app.py
unac/correction/__init__.py
unac/correction/ict_bindings.py
unac/correction/interface.py
unac/correction/isocor_bindings.py
unac/correction/isocorrector_bindings.py
unac/correction/naive.py
unac/correction/registry.py
unac/external/README
unac/external/ICT/README
unac/external/ICT/ict.pl
unac/external/ICT/Bio/IsotopeCorrection/Chemicals.pm
unac/external/ICT/Bio/IsotopeCorrection/NaturalIsotopes.pm
unac/setup/isocorrector.py
unac/setup/__pycache__/isocorrector.cpython-311.pyc
unac/util/__init__.py
unac/util/compare.py
unac/util/config.py
unac/util/data.py
unac/util/exports.py
unac/util/imports.py
unac/util/plots.py
unac-0.2.1.dist-info/licenses/LICENSE
unac-0.2.1.dist-info/METADATA
unac-0.2.1.dist-info/WHEEL
unac-0.2.1.dist-info/entry_points.txt
unac-0.2.1.dist-info/top_level.txt
unac-0.2.1.dist-info/RECORD
